vk_data_collector/__init__.py
vk_data_collector/client/client.py
vk_data_collector/collector/collector.py
vk_data_collector/service/service.py
vk_data_collector/types/methods/groups_get_by_id.py
vk_data_collector/types/methods/wall_get.py
vk_data_collector/types/methods/wall_get_comments.py
vk_data_collector/types/objects/comment.py
vk_data_collector/types/objects/comments.py
vk_data_collector/types/objects/copyright.py
vk_data_collector/types/objects/donut.py
vk_data_collector/types/objects/geo.py
vk_data_collector/types/objects/group.py
vk_data_collector/types/objects/likes.py
vk_data_collector/types/objects/place.py
vk_data_collector/types/objects/post.py
vk_data_collector/types/objects/post_source.py
vk_data_collector/types/objects/reposts.py
vk_data_collector/types/objects/user.py
vk_data_collector/types/objects/views.py
vk_data_collector/utils/decorators/rate_limited.py
vk_data_collector-0.2.4.dist-info/METADATA
vk_data_collector-0.2.4.dist-info/WHEEL
vk_data_collector-0.2.4.dist-info/licenses/LICENSE
vk_data_collector-0.2.4.dist-info/RECORD
