Metadata-Version: 2.4
Name: vk-data-collector
Version: 0.2.4
Summary: A Python library for collecting data from VK (VKontakte) social network
Project-URL: Homepage, https://github.com/nymless/vk-data-collector
Project-URL: Documentation, https://github.com/nymless/vk-data-collector#readme
Project-URL: Repository, https://github.com/nymless/vk-data-collector.git
Project-URL: Issues, https://github.com/nymless/vk-data-collector/issues
Author-email: Ivan Baklanov <nymless.ib@gmail.com>
License: MIT
License-File: LICENSE
Keywords: data-collection,social-media,vk,vkontakte
Classifier: Development Status :: 3 - Alpha
Classifier: Intended Audience :: Developers
Classifier: License :: OSI Approved :: MIT License
Classifier: Programming Language :: Python :: 3
Classifier: Programming Language :: Python :: 3.9
Classifier: Programming Language :: Python :: 3.10
Classifier: Programming Language :: Python :: 3.11
Classifier: Topic :: Internet :: WWW/HTTP
Classifier: Topic :: Software Development :: Libraries :: Python Modules
Requires-Python: >=3.9
Requires-Dist: requests>=2.32.3
